<?xml version="1.0" encoding="UTF-8"?>
<monster name="Caterpie" nameDescription="a caterpie" race="bug" experience="100" speed="208" manacost="0">
    <health now="200" max="200"/>
    <look type="32" corpse="11849"/>
    <targetchange interval="2000" chance="0"/>
    <strategy attack="100" defense="0"/>
    <flags>
        <flag summonable="1"/>
        <flag attackable="1"/>
        <flag hostile="1"/>
        <flag passive="1"/>
        <flag illusionable="1"/>
        <flag convinceable="1"/>
        <flag pushable="1"/>
        <flag canpushitems="0"/>
        <flag canpushcreatures="0"/>
        <flag targetdistance="1"/>
        <flag staticattack="97"/>
        <flag runonhealth="0"/>
    </flags>
	<status>
		<poke HP="45"/>
		<poke Attack="30"/>
		<poke Defense="35"/>
		<poke SpAtk="20"/>
		<poke SpDef="20"/>
		<poke Speed="45"/>
		<poke type1="bug"/>
		<poke type2="no type"/>
	</status>
    <attacks>
		<attack name="melee" interval="2000" chance="100" range="1" min="-50" max="-100"/>
		<attack name="Headbutt" interval="1701" chance="30" range="1"/>
		<attack name="String Shot" interval="1702" chance="30" range="6"/>
		<attack name="Bug Bite" interval="1653" chance="60" range="1"/>
    </attacks>
    <defenses armor="0" defense="0"/>
    <voices interval="5000" chance="10">
        <voice sentence="CATERPIE!"/>
    </voices>
    <loot>
    </loot>
    <script>
        <event name="Spawn"/>
    </script>
</monster>
