<?xml version="1.0" encoding="UTF-8"?>
<monster name="Meditite" nameDescription="a meditite" race="ghost" experience="1100" speed="217" manacost="0">
    <health now="130" max="130"/>
    <look type="1888" corpse="14723"/>
    <targetchange interval="2000" chance="0"/>
    <strategy attack="100" defense="0"/>
    <flags>
        <flag summonable="1"/>
        <flag attackable="1"/>
        <flag hostile="1"/>
        <flag illusionable="1"/>
        <flag convinceable="1"/>
        <flag pushable="1"/>
        <flag canpushitems="0"/>
        <flag canpushcreatures="0"/>
        <flag targetdistance="1"/>
        <flag staticattack="97"/>
        <flag runonhealth="0"/>
    </flags>
	<status>
		<poke HP="30"/>
		<poke Attack="40"/>
		<poke Defense="55"/>
		<poke SpAtk="40"/>
		<poke SpDef="55"/>
		<poke Speed="60"/>
		<poke type1="fighting"/>
		<poke type2="psychic"/>
	</status>
    <attacks>
		<attack name="melee" interval="2000" chance="100" range="1" min="-50" max="-100"/>
		<attack name="Triple Punch" interval="831" chance="17" range="1"/>
		<attack name="Mega Kick" interval="832" chance="17" range="1"/>
		<attack name="Drain Punch" interval="833" chance="17" range="1"/>
		<attack name="Confusion" interval="744" chance="34" range="6"/>
		<attack name="Psychic" interval="1282" chance="12" range="6"/>
		<attack name="Hi Jump Kick" interval="2358" chance="6" range="6"/>
    </attacks>
    <defenses armor="0" defense="0"/>
    <voices interval="5000" chance="10">
        <voice sentence="Medichan!"/>
    </voices>
    <loot>
		
    </loot>
    <script>
        <event name="Spawn"/>
    </script>
</monster>
